confugue/__init__.py
confugue/version.py
confugue-0.1.1.dist-info/LICENSE
confugue-0.1.1.dist-info/METADATA
confugue-0.1.1.dist-info/WHEEL
confugue-0.1.1.dist-info/top_level.txt
confugue-0.1.1.dist-info/RECORD
