Metadata-Version: 2.1
Name: confugue
Version: 0.1.1
Summary: Hierarchical configuration framework
Home-page: https://github.com/cifkao/confugue
Author: Ondřej Cífka
Author-email: ondra@cifka.com
License: UNKNOWN
Platform: UNKNOWN
Classifier: Programming Language :: Python :: 3
Classifier: Programming Language :: Python :: 3 :: Only
Classifier: Programming Language :: Python :: 3.5
Classifier: Programming Language :: Python :: 3.6
Classifier: Programming Language :: Python :: 3.7
Classifier: Programming Language :: Python :: 3.8
Classifier: Programming Language :: Python :: 3.9
Classifier: Operating System :: OS Independent
Classifier: License :: OSI Approved :: BSD License
Classifier: Topic :: Software Development :: Libraries :: Python Modules
Classifier: Topic :: Utilities
Classifier: Intended Audience :: Developers
Classifier: Intended Audience :: Science/Research
Requires-Python: >=3.5
Requires-Dist: pyyaml (>=5.1)
Requires-Dist: wrapt (>=1.10.0)
